[
  {
    "Сотрудник": "Иван",
    "Магазин": "Магазин 1",
    "Должность": "Продавец",
    "Расписание": [
        {
            "Дата": "2023-05-01",
            "ПланРаботы": "08:00 - 17:00",
            "ФактРаботы": "09:15 - 17:30",
            "Прогулы": 0,
            "Опоздания": 1,
            "РанниеУходы": 0
        },
        {
            "Дата": "2023-05-02",
            "ПланРаботы": "09:00 - 17:00",
            "ФактРаботы": "09:15 - 16:30",
            "Прогулы": 0,
            "Опоздания": 1,
            "РанниеУходы": 1
        },
        {
            "Дата": "2023-05-03",
            "ПланРаботы": "09:00 - 17:00",
            "ФактРаботы": "прогул",
            "Прогулы": 1,
            "Опоздания": 0,
            "РанниеУходы": 1
        },
        {
            "Дата": "2023-05-04",
            "ПланРаботы": "09:00 - 17:00",
            "ФактРаботы": "09:15 - 17:30",
            "Прогулы": 0,
            "Опоздания": 1,
            "РанниеУходы": 0
        },
        {
          "Дата": "2023-05-05",
          "ПланРаботы": "09:00 - 17:00",
          "ФактРаботы": "09:15 - 17:30",
          "Прогулы": 0,
          "Опоздания": 1,
          "РанниеУходы": 0
        },
        {
          "Дата": "2023-05-06",
          "ПланРаботы": "выходной",
          "ФактРаботы": "выходной",
          "Прогулы": 0,
          "Опоздания": 0,
          "РанниеУходы": 0
        }
    ]
  },
  {
    "Сотрудник": "Dima",
    "Магазин": "Магазин 2",
    "Должность": "Продавец",
    "Расписание": [
        {
            "Дата": "2023-05-01",
            "ПланРаботы": "08:00 - 17:00",
            "ФактРаботы": "09:15 - 17:30",
            "Прогулы": 0,
            "Опоздания": 1,
            "РанниеУходы": 0
        },
        {
            "Дата": "2023-05-02",
            "ПланРаботы": "09:00 - 17:00",
            "ФактРаботы": "09:00 - 17:30",
            "Прогулы": 0,
            "Опоздания": 0,
            "РанниеУходы": 0
        },
        {
            "Дата": "2023-05-03",
            "ПланРаботы": "09:00 - 17:00",
            "ФактРаботы": "09:00 - 17:30",
            "Прогулы": 0,
            "Опоздания": 0,
            "РанниеУходы": 0
        },
        {
            "Дата": "2023-05-04",
            "ПланРаботы": "09:00 - 17:00",
            "ФактРаботы": "прогул",
            "Прогулы": 1,
            "Опоздания": 0,
            "РанниеУходы": 0
        },
        {
          "Дата": "2023-05-05",
          "ПланРаботы": "09:00 - 17:00",
          "ФактРаботы": "прогул",
          "Прогулы": 1,
          "Опоздания": 0,
          "РанниеУходы": 0
        },
        {
          "Дата": "2023-05-06",
          "ПланРаботы": "выходной",
          "ФактРаботы": "выходной",
          "Прогулы": 0,
          "Опоздания": 0,
          "РанниеУходы": 0
        }
    ]
  }
]